adsc/__init__.py
adsc/config.py
adsc/main.py
adsc/systemd.py
adsc-1.0.5.dist-info/METADATA
adsc-1.0.5.dist-info/WHEEL
adsc-1.0.5.dist-info/entry_points.txt
adsc-1.0.5.dist-info/top_level.txt
adsc-1.0.5.dist-info/RECORD
