Metadata-Version: 2.4
Name: adsc
Version: 1.0.5
Summary: AdsC Telegram multi-account broadcast bot
Author-email: AdsC <adsc.bot@gmail.com>
Requires-Python: >=3.9
Requires-Dist: telethon>=1.34.0
Requires-Dist: python-telegram-bot==20.7
